{"title":"可访问性检查","slug":"legacy-skill-internal-accessibility-check-46cdd1","summary":"按 WCAG 2.1 标准检查产品的色彩对比度、键盘导航、语义标签和屏幕阅读器适配，让更多用户能无障碍使用产品。","category":"Skill库","tags":["Skill","审查交付","可访问性","WCAG","对比度","a11y","无障碍","键盘导航"],"featured":false,"order":129,"level":2,"updatedAt":"2026-07-03","wordCount":941,"sourceUrl":"https://ruiying1541.github.io/design-skills/skills/accessibility-check","html":"<h2>为什么可访问性很重要？</h2>\n<ul><li>全球约 <strong>15%</strong> 的人口存在某种形式的残障（WHO 数据）</li><li>可访问性好的产品对<strong>所有人</strong>都更易用（强光下看手机、单手操作、嘈杂环境等）</li><li>许多国家和地区的法规要求数字产品达到 WCAG AA 级别</li><li>可访问性问题在设计阶段修复的成本，是开发后修复的 <strong>1/10</strong></li></ul>\n<hr>\n<h2>WCAG 三个合规等级</h2>\n<table><tr><th>等级</th><th>要求</th><th>适用场景</th></tr><tr><td>A</td><td>最低要求</td><td>不推荐只做到 A</td></tr><tr><td><strong>AA</strong></td><td><strong>推荐标准</strong></td><td><strong>大多数产品应达到此标准</strong></td></tr><tr><td>AAA</td><td>最高要求</td><td>政府/医疗/教育类产品</td></tr></table>\n<hr>\n<h2>色彩对比度（最常见问题）</h2>\n<p>WCAG AA 对比度要求：</p>\n<table><tr><th>场景</th><th>最低对比度</th></tr><tr><td>正常文本（&lt; 18px）</td><td><strong>4.5 : 1</strong></td></tr><tr><td>大文本（≥ 18px 常规 / ≥ 14px 加粗）</td><td><strong>3 : 1</strong></td></tr><tr><td>UI 组件、图标、图表</td><td><strong>3 : 1</strong></td></tr><tr><td>装饰性元素</td><td>无要求</td></tr></table>\n<h3>常见错误案例</h3>\n<pre><code>❌ 灰色文字 #9CA3AF 在白色背景（对比度 2.7:1）— 不达标\n✅ 灰色文字 #6B7280 在白色背景（对比度 4.6:1）— AA 通过\n\n❌ 白色文字在浅黄色按钮 #FCD34D（对比度 1.5:1）— 不达标  \n✅ 深色文字 #1F2937 在浅黄色按钮（对比度 11:1）— 通过</code></pre>\n<h3>如何检测</h3>\n<p>1. <strong>Figma 插件</strong>：Contrast 、A11y Annotation Kit 2. <strong>在线工具</strong>：<a href=\"https://webaim.org/resources/contrastchecker/\" target=\"_blank\" rel=\"noreferrer\">Contrast Checker</a> 3. <strong>代码检查</strong>：axe DevTools Chrome 插件（自动扫描页面）</p>\n<hr>\n<h2>触摸目标尺寸</h2>\n<p>移动端可触摸区域最小应为 <strong>44×44pt</strong>（iOS HIG 要求），Android 建议 <strong>48×48dp</strong>。</p>\n<p>即使图标只有 24px，其可触摸区域也应扩展到 44px：</p>\n<pre><code>/* 正确做法：用 padding 扩大点击区域 */\n.icon-button {\n  padding: 10px;  /* 24px 图标 + 10px×2 = 44px */\n}</code></pre>\n<hr>\n<h2>键盘可访问性</h2>\n<p>所有可交互元素必须：</p>\n<ul><li>[ ] 可以用 Tab 键聚焦</li><li>[ ] 聚焦状态有清晰的视觉反馈（不能只靠颜色区分）</li><li>[ ] 可以用 Enter/Space 触发</li><li>[ ] 焦点顺序符合视觉阅读顺序</li><li>[ ] 弹窗打开后焦点锁定在弹窗内，关闭后焦点返回触发元素</li></ul>\n<hr>\n<h2>颜色非唯一信息传递</h2>\n<p><strong>不要</strong>只用颜色来传递状态：</p>\n<pre><code>❌ 错误：红色 = 错误，绿色 = 成功（色盲用户无法区分）\n✅ 正确：红色图标 + &quot;输入格式错误&quot; 文字提示\n✅ 正确：绿色 + ✓ 图标 + &quot;保存成功&quot; 文字</code></pre>\n<hr>\n<h2>图片替代文字（Alt Text）</h2>\n<pre><code>&lt;!-- 有含义的图片 --&gt;\n&lt;img src=&quot;profile.jpg&quot; alt=&quot;用户张三的头像&quot;&gt;\n\n&lt;!-- 装饰性图片（屏幕阅读器跳过） --&gt;\n&lt;img src=&quot;decoration.png&quot; alt=&quot;&quot; role=&quot;presentation&quot;&gt;\n\n&lt;!-- 图标按钮 --&gt;\n&lt;button aria-label=&quot;删除这条评论&quot;&gt;\n  &lt;svg&gt;...&lt;/svg&gt;\n&lt;/button&gt;</code></pre>\n<hr>\n<h2>可访问性检查 Checklist</h2>\n<h3>颜色与视觉</h3>\n<ul><li>[ ] 正文文字对比度 ≥ 4.5:1</li><li>[ ] 大文字对比度 ≥ 3:1</li><li>[ ] UI 组件对比度 ≥ 3:1</li><li>[ ] 不仅凭颜色传递信息</li></ul>\n<h3>操作与交互</h3>\n<ul><li>[ ] 所有交互元素可键盘聚焦</li><li>[ ] 聚焦状态有明显视觉反馈</li><li>[ ] 触摸目标 ≥ 44×44pt</li><li>[ ] 链接/按钮描述文字有意义（非「点击这里」）</li></ul>\n<h3>内容</h3>\n<ul><li>[ ] 所有图片有 alt 文字（装饰图为空 alt）</li><li>[ ] 视频有字幕或文字说明</li><li>[ ] 页面标题唯一且有描述性</li><li>[ ] 表单 input 有对应 label</li></ul>\n<hr>\n<h2>AI 辅助使用</h2>\n<p><strong>触发词示例：</strong> &gt; &quot;检查以下颜色组合是否满足 WCAG AA 标准：文字颜色 #6B7280，背景颜色 #FFFFFF，字号 14px&quot;</p>\n<p>&gt; &quot;帮我为以下 5 个按钮状态生成符合可访问性规范的 aria-label：搜索按钮、关闭弹窗、删除评论、收藏文章、分享链接&quot;</p>"}
