{"title":"设计交付规范","slug":"legacy-skill-internal-design-handoff-94a572","summary":"建立设计师向开发工程师交付设计稿的完整规范，减少沟通成本，确保还原度，避免「设计师画一套，开发做一套」。","category":"Skill库","tags":["Skill","审查交付","设计交付","Figma","标注","切图","开发协作","还原度"],"featured":false,"order":132,"level":2,"updatedAt":"2026-07-03","wordCount":851,"sourceUrl":"https://ruiying1541.github.io/design-skills/skills/design-handoff","html":"<h2>为什么需要交付规范？</h2>\n<p>缺乏规范的设计交付会导致：</p>\n<ul><li>开发找不到切图，频繁打扰设计师</li><li>同一元素在设计稿和代码中间距相差 2-4px</li><li>颜色值传递错误（截图取色 vs 精确色值）</li><li>交互说明口头传达，开发实现时遗忘</li></ul>\n<p>一套清晰的交付规范能<strong>将沟通成本降低 60% 以上</strong>。</p>\n<hr>\n<h2>Figma 文件结构规范</h2>\n<h3>页面命名</h3>\n<pre><code>Cover          ← 封面，展示项目信息\nDesign         ← 主设计稿（按功能模块分 Section）\nComponents     ← 本项目专用组件（非通用组件库）\nPrototype      ← 原型流程\nArchive        ← 历史版本归档（不删除）</code></pre>\n<h3>Section 命名</h3>\n<pre><code>🔵 [功能模块名] — 开发中\n✅ [功能模块名] — 已交付\n🟡 [功能模块名] — 待评审</code></pre>\n<h3>Frame 命名</h3>\n<pre><code>格式：[平台] / [页面名] / [状态]\n\n示例：\n  iOS / 首页 / 默认\n  iOS / 首页 / 加载中\n  Web / 用户中心 / 已登录</code></pre>\n<hr>\n<h2>交付前 Checklist</h2>\n<h3>视觉层</h3>\n<ul><li>[ ] 所有文字使用 Text Styles（非手动输入字号）</li><li>[ ] 所有颜色使用 Color Styles 或 Variables</li><li>[ ] 所有间距使用整数值（无小数点）</li><li>[ ] 所有元素正确命名（非 Frame 123、Rectangle 456）</li></ul>\n<h3>资源层</h3>\n<ul><li>[ ] 需要切图的元素已标记为 Export</li><li>[ ] 切图按命名规范命名（见下方）</li><li>[ ] 大图/背景图已提供 1x 和 2x</li><li>[ ] 图标已导出 SVG 格式</li></ul>\n<h3>说明层</h3>\n<ul><li>[ ] 交互说明已用 Figma 注释或单独说明页标注</li><li>[ ] 特殊动效（非常规过渡）有详细描述</li><li>[ ] 边界情况（空状态、加载状态、错误状态）已设计</li><li>[ ] 不同屏幕尺寸适配方案已说明</li></ul>\n<hr>\n<h2>切图命名规范</h2>\n<p>格式：<code>[类型前缀]_[模块名]_[描述]_[倍率].[格式]</code></p>\n<table><tr><th>类型</th><th>前缀</th><th>示例</th></tr><tr><td>图标</td><td><code>ic_</code></td><td><code>ic_home_filled@2x.png</code></td></tr><tr><td>背景图</td><td><code>bg_</code></td><td><code>bg_login_top.jpg</code></td></tr><tr><td>插图/空状态</td><td><code>img_</code></td><td><code>img_empty_search.png</code></td></tr><tr><td>Logo</td><td><code>logo_</code></td><td><code>logo_main@2x.png</code></td></tr><tr><td>Banner</td><td><code>banner_</code></td><td><code>banner_new_year.jpg</code></td></tr></table>\n<p>命名规则：</p>\n<ul><li>全小写，使用下划线分隔</li><li>不含中文和特殊字符</li><li>iOS 端附加 <code>@2x</code> <code>@3x</code>，Android 端放入 <code>mdpi/hdpi/xhdpi</code> 目录</li></ul>\n<hr>\n<h2>颜色交付方式</h2>\n<p><strong>不要</strong>：截图给开发取色（误差大） <strong>推荐</strong>：</p>\n<p>1. <strong>Figma Dev Mode</strong>：开发直接在 Figma 复制色值（HEX/RGB/HSL） 2. <strong>Design Token 文件</strong>：直接提供 <code>tokens.json</code>，开发导入 3. <strong>Figma Variables</strong>：使用 Figma 变量系统，一键导出 token</p>\n<hr>\n<h2>交互说明模板</h2>\n<p>对于复杂交互，在 Figma 旁附上说明框：</p>\n<pre><code>【触发条件】用户点击「提交」按钮\n【动画类型】Spring 弹性动画\n【持续时间】300ms\n【缓动函数】ease-out\n【特殊说明】\n  - 按钮点击后进入 Loading 状态，禁止重复点击\n  - 成功后 Toast 停留 2 秒后自动消失\n  - 失败时 Input 边框变红，显示错误文字</code></pre>\n<hr>\n<h2>与开发的协作流程</h2>\n<pre><code>1. 设计完成 → 设计 Review（自查 checklist）\n2. 产品 Review → 修改意见同步设计\n3. 标记 Section 为「待评审」→ 通知开发评审\n4. 开发提出疑问 → 48h 内设计回复\n5. 开发完成 → 设计走查（还原度检查）\n6. 对齐问题 → 记录对齐单，分优先级修复</code></pre>\n<hr>\n<h2>AI 辅助使用</h2>\n<p><strong>触发词示例：</strong> &gt; &quot;帮我生成一个设计稿交付前的完整 checklist，包括视觉规范检查、资源输出检查和交互说明检查三个维度&quot;</p>"}
